{
    "_links": {
        "self": {
            "href": "http:\/\/default\/taxonomy\/term\/3?_format=hal_json"
        },
        "type": {
            "href": "http:\/\/drupal.org\/rest\/type\/taxonomy_term\/technologies"
        }
    },
    "tid": [
        {
            "value": 3
        }
    ],
    "uuid": [
        {
            "value": "9bde9b1c-07e1-489d-b347-f4eaed6cc893"
        }
    ],
    "langcode": [
        {
            "value": "en",
            "lang": "en"
        }
    ],
    "vid": [
        {
            "target_id": "technologies"
        }
    ],
    "name": [
        {
            "value": "SASS",
            "lang": "en"
        }
    ],
    "weight": [
        {
            "value": 0
        }
    ],
    "changed": [
        {
            "value": "2018-03-04T17:36:40+00:00",
            "lang": "en",
            "format": "Y-m-d\\TH:i:sP"
        }
    ],
    "default_langcode": [
        {
            "value": true,
            "lang": "en"
        }
    ],
    "path": [
        {
            "alias": null,
            "pid": null,
            "langcode": "en",
            "lang": "en"
        }
    ]
}